qodex_skud_bus/__init__.py
qodex_skud_bus/event_functions.py
qodex_skud_bus/functions.py
qodex_skud_bus/main.py
qodex_skud_bus/points_logic.py
qodex_skud_bus/settings.py
qodex_skud_bus/exceptions/__init__.py
qodex_skud_bus/exceptions/exceptions.py
qodex_skud_bus/tests/__init__.py
qodex_skud_bus/tests/functionst_test.py
qodex_skud_bus/tests/main_test.py
qodex_skud_bus/tests/main_test_qdk.py
qodex_skud_bus/tests/test_qdk.py
qodex_skud_bus/tools/__init__.py
qodex_skud_bus/tools/decorators.py
qodex_skud_bus/tools/exceptions.py
qodex_skud_bus-0.0.71.dist-info/LICENSE
qodex_skud_bus-0.0.71.dist-info/METADATA
qodex_skud_bus-0.0.71.dist-info/WHEEL
qodex_skud_bus-0.0.71.dist-info/top_level.txt
qodex_skud_bus-0.0.71.dist-info/RECORD
