Metadata-Version: 2.1
Name: qodex-skud-bus
Version: 0.0.71
Summary: UNKNOWN
Home-page: UNKNOWN
Author: PunchyArchy
Author-email: ksmdrmvscthny@gmail.com
License: UNKNOWN
Platform: UNKNOWN
License-File: LICENSE
Requires-Dist: qodex-pi
Requires-Dist: sigur-interact
Requires-Dist: gbarrier
Requires-Dist: gphotocell
